{
    "description": "",
    "tags": [],
    "size": {
        "height": 572,
        "width": 572
    },
    "objects": [
        {
            "id": 553563659,
            "classId": 2703473,
            "description": "",
            "geometryType": "polygon",
            "labelerLogin": "8holztisch8@gmx.ch",
            "createdAt": "2020-11-09T19:37:00.317Z",
            "updatedAt": "2020-11-09T19:37:42.538Z",
            "tags": [],
            "classTitle": "Player",
            "points": {
                "exterior": [
                    [
                        452,
                        303
                    ],
                    [
                        452,
                        357
                    ],
                    [
                        470,
                        375
                    ],
                    [
                        471,
                        382
                    ],
                    [
                        471,
                        386
                    ],
                    [
                        468,
                        388
                    ],
                    [
                        463,
                        391
                    ],
                    [
                        458,
                        392
                    ],
                    [
                        453,
                        394
                    ],
                    [
                        448,
                        397
                    ],
                    [
                        446,
                        398
                    ],
                    [
                        441,
                        400
                    ],
                    [
                        440,
                        402
                    ],
                    [
                        439,
                        406
                    ],
                    [
                        439,
                        408
                    ],
                    [
                        437,
                        411
                    ],
                    [
                        432,
                        414
                    ],
                    [
                        428,
                        414
                    ],
                    [
                        423,
                        414
                    ],
                    [
                        418,
                        413
                    ],
                    [
                        415,
                        410
                    ],
                    [
                        414,
                        405
                    ],
                    [
                        420,
                        402
                    ],
                    [
                        425,
                        399
                    ],
                    [
                        427,
                        392
                    ],
                    [
                        430,
                        389
                    ],
                    [
                        435,
                        386
                    ],
                    [
                        440,
                        383
                    ],
                    [
                        445,
                        381
                    ],
                    [
                        442,
                        379
                    ],
                    [
                        438,
                        377
                    ],
                    [
                        434,
                        372
                    ],
                    [
                        429,
                        374
                    ],
                    [
                        424,
                        375
                    ],
                    [
                        421,
                        373
                    ],
                    [
                        417,
                        376
                    ],
                    [
                        413,
                        378
                    ],
                    [
                        408,
                        379
                    ],
                    [
                        406,
                        381
                    ],
                    [
                        401,
                        384
                    ],
                    [
                        394,
                        384
                    ],
                    [
                        392,
                        387
                    ],
                    [
                        391,
                        390
                    ],
                    [
                        386,
                        392
                    ],
                    [
                        383,
                        392
                    ],
                    [
                        379,
                        391
                    ],
                    [
                        375,
                        388
                    ],
                    [
                        378,
                        383
                    ],
                    [
                        386,
                        379
                    ],
                    [
                        391,
                        377
                    ],
                    [
                        392,
                        370
                    ],
                    [
                        398,
                        366
                    ],
                    [
                        406,
                        365
                    ],
                    [
                        411,
                        362
                    ],
                    [
                        411,
                        357
                    ],
                    [
                        410,
                        353
                    ],
                    [
                        408,
                        348
                    ],
                    [
                        408,
                        343
                    ],
                    [
                        410,
                        339
                    ],
                    [
                        414,
                        336
                    ],
                    [
                        413,
                        334
                    ],
                    [
                        413,
                        330
                    ],
                    [
                        413,
                        326
                    ],
                    [
                        415,
                        321
                    ],
                    [
                        417,
                        317
                    ],
                    [
                        420,
                        313
                    ],
                    [
                        423,
                        309
                    ],
                    [
                        428,
                        308
                    ],
                    [
                        434,
                        309
                    ],
                    [
                        436,
                        309
                    ],
                    [
                        441,
                        311
                    ],
                    [
                        444,
                        311
                    ],
                    [
                        446,
                        308
                    ],
                    [
                        447,
                        305
                    ]
                ],
                "interior": []
            }
        },
        {
            "id": 553563661,
            "classId": 2703473,
            "description": "",
            "geometryType": "polygon",
            "labelerLogin": "8holztisch8@gmx.ch",
            "createdAt": "2020-11-09T19:37:42.459Z",
            "updatedAt": "2020-11-09T19:38:22.443Z",
            "tags": [],
            "classTitle": "Player",
            "points": {
                "exterior": [
                    [
                        250,
                        256
                    ],
                    [
                        291,
                        246
                    ],
                    [
                        294,
                        249
                    ],
                    [
                        297,
                        251
                    ],
                    [
                        297,
                        255
                    ],
                    [
                        296,
                        257
                    ],
                    [
                        293,
                        260
                    ],
                    [
                        290,
                        261
                    ],
                    [
                        287,
                        261
                    ],
                    [
                        285,
                        262
                    ],
                    [
                        287,
                        264
                    ],
                    [
                        288,
                        267
                    ],
                    [
                        289,
                        270
                    ],
                    [
                        291,
                        274
                    ],
                    [
                        293,
                        277
                    ],
                    [
                        294,
                        280
                    ],
                    [
                        296,
                        283
                    ],
                    [
                        298,
                        286
                    ],
                    [
                        302,
                        288
                    ],
                    [
                        304,
                        291
                    ],
                    [
                        305,
                        295
                    ],
                    [
                        302,
                        299
                    ],
                    [
                        300,
                        301
                    ],
                    [
                        297,
                        304
                    ],
                    [
                        294,
                        307
                    ],
                    [
                        290,
                        309
                    ],
                    [
                        288,
                        311
                    ],
                    [
                        286,
                        314
                    ],
                    [
                        287,
                        318
                    ],
                    [
                        288,
                        321
                    ],
                    [
                        290,
                        325
                    ],
                    [
                        292,
                        329
                    ],
                    [
                        294,
                        335
                    ],
                    [
                        295,
                        338
                    ],
                    [
                        298,
                        341
                    ],
                    [
                        299,
                        345
                    ],
                    [
                        300,
                        348
                    ],
                    [
                        298,
                        351
                    ],
                    [
                        293,
                        354
                    ],
                    [
                        291,
                        354
                    ],
                    [
                        289,
                        348
                    ],
                    [
                        290,
                        342
                    ],
                    [
                        288,
                        338
                    ],
                    [
                        284,
                        333
                    ],
                    [
                        282,
                        328
                    ],
                    [
                        279,
                        322
                    ],
                    [
                        277,
                        317
                    ],
                    [
                        274,
                        320
                    ],
                    [
                        272,
                        322
                    ],
                    [
                        272,
                        326
                    ],
                    [
                        274,
                        331
                    ],
                    [
                        276,
                        335
                    ],
                    [
                        279,
                        340
                    ],
                    [
                        281,
                        342
                    ],
                    [
                        283,
                        347
                    ],
                    [
                        285,
                        350
                    ],
                    [
                        287,
                        353
                    ],
                    [
                        288,
                        357
                    ],
                    [
                        286,
                        360
                    ],
                    [
                        280,
                        359
                    ],
                    [
                        277,
                        357
                    ],
                    [
                        272,
                        356
                    ],
                    [
                        270,
                        353
                    ],
                    [
                        267,
                        348
                    ],
                    [
                        270,
                        346
                    ],
                    [
                        271,
                        343
                    ],
                    [
                        268,
                        340
                    ],
                    [
                        265,
                        336
                    ],
                    [
                        262,
                        333
                    ],
                    [
                        259,
                        329
                    ],
                    [
                        255,
                        325
                    ],
                    [
                        254,
                        320
                    ],
                    [
                        253,
                        315
                    ],
                    [
                        253,
                        311
                    ],
                    [
                        255,
                        305
                    ],
                    [
                        259,
                        302
                    ],
                    [
                        263,
                        301
                    ],
                    [
                        263,
                        297
                    ],
                    [
                        263,
                        293
                    ],
                    [
                        262,
                        289
                    ],
                    [
                        262,
                        285
                    ],
                    [
                        261,
                        281
                    ],
                    [
                        260,
                        277
                    ],
                    [
                        258,
                        275
                    ],
                    [
                        254,
                        276
                    ],
                    [
                        251,
                        279
                    ],
                    [
                        248,
                        280
                    ],
                    [
                        246,
                        283
                    ],
                    [
                        242,
                        287
                    ],
                    [
                        240,
                        289
                    ],
                    [
                        239,
                        278
                    ],
                    [
                        243,
                        273
                    ],
                    [
                        245,
                        269
                    ],
                    [
                        245,
                        265
                    ],
                    [
                        247,
                        263
                    ],
                    [
                        246,
                        261
                    ],
                    [
                        243,
                        261
                    ],
                    [
                        241,
                        260
                    ],
                    [
                        241,
                        258
                    ],
                    [
                        244,
                        257
                    ],
                    [
                        248,
                        256
                    ]
                ],
                "interior": []
            }
        }
    ]
}