{
    "description": "",
    "tags": [],
    "size": {
        "height": 572,
        "width": 572
    },
    "objects": [
        {
            "id": 553562646,
            "classId": 2703473,
            "description": "",
            "geometryType": "polygon",
            "labelerLogin": "8holztisch8@gmx.ch",
            "createdAt": "2020-11-09T18:17:05.425Z",
            "updatedAt": "2020-11-09T18:18:05.730Z",
            "tags": [],
            "classTitle": "Player",
            "points": {
                "exterior": [
                    [
                        284,
                        282
                    ],
                    [
                        291,
                        281
                    ],
                    [
                        296,
                        282
                    ],
                    [
                        302,
                        280
                    ],
                    [
                        306,
                        280
                    ],
                    [
                        309,
                        282
                    ],
                    [
                        311,
                        285
                    ],
                    [
                        313,
                        288
                    ],
                    [
                        315,
                        291
                    ],
                    [
                        317,
                        294
                    ],
                    [
                        318,
                        296
                    ],
                    [
                        320,
                        299
                    ],
                    [
                        321,
                        301
                    ],
                    [
                        324,
                        309
                    ],
                    [
                        327,
                        315
                    ],
                    [
                        327,
                        319
                    ],
                    [
                        324,
                        322
                    ],
                    [
                        320,
                        323
                    ],
                    [
                        317,
                        323
                    ],
                    [
                        312,
                        321
                    ],
                    [
                        311,
                        324
                    ],
                    [
                        310,
                        329
                    ],
                    [
                        311,
                        333
                    ],
                    [
                        313,
                        337
                    ],
                    [
                        315,
                        341
                    ],
                    [
                        317,
                        344
                    ],
                    [
                        319,
                        348
                    ],
                    [
                        321,
                        352
                    ],
                    [
                        322,
                        356
                    ],
                    [
                        322,
                        364
                    ],
                    [
                        320,
                        368
                    ],
                    [
                        317,
                        369
                    ],
                    [
                        312,
                        369
                    ],
                    [
                        308,
                        368
                    ],
                    [
                        305,
                        365
                    ],
                    [
                        302,
                        365
                    ],
                    [
                        304,
                        370
                    ],
                    [
                        306,
                        373
                    ],
                    [
                        305,
                        375
                    ],
                    [
                        302,
                        376
                    ],
                    [
                        299,
                        376
                    ],
                    [
                        296,
                        375
                    ],
                    [
                        296,
                        370
                    ],
                    [
                        292,
                        371
                    ],
                    [
                        288,
                        370
                    ],
                    [
                        286,
                        367
                    ],
                    [
                        286,
                        363
                    ],
                    [
                        284,
                        355
                    ],
                    [
                        283,
                        348
                    ],
                    [
                        283,
                        342
                    ],
                    [
                        282,
                        334
                    ],
                    [
                        281,
                        330
                    ],
                    [
                        281,
                        324
                    ],
                    [
                        280,
                        318
                    ],
                    [
                        280,
                        313
                    ],
                    [
                        279,
                        308
                    ],
                    [
                        279,
                        302
                    ],
                    [
                        278,
                        297
                    ],
                    [
                        278,
                        293
                    ],
                    [
                        277,
                        289
                    ],
                    [
                        279,
                        286
                    ]
                ],
                "interior": []
            }
        }
    ]
}